TMDA/Address.py
TMDA/Auth.py
TMDA/AutoResponse.py
TMDA/Cookie.py
TMDA/Defaults.py
TMDA/Deliver.py
TMDA/Errors.py
TMDA/FilterParser.py
TMDA/MTA.py
TMDA/MessageLogger.py
TMDA/Pending.py
TMDA/SMTP.py
TMDA/Util.py
TMDA/Version.py
TMDA/__init__.py
TMDA/filter.py
TMDA/rfilter.py
TMDA/inject.py
TMDA/address.py
TMDA/ofmipd.py
TMDA/check_address.py
TMDA/keygen.py
TMDA/pending.py
TMDA/sendmail.py
TMDA/Queue/MaildirQueue.py
TMDA/Queue/OriginalQueue.py
TMDA/Queue/Queue.py
TMDA/Queue/Util.py
TMDA/Queue/__init__.py
TMDA/templates/bounce_expired_dated.txt
TMDA/templates/bounce_fail_dated.txt
TMDA/templates/bounce_fail_keyword.txt
TMDA/templates/bounce_fail_sender.txt
TMDA/templates/bounce_incoming.txt
TMDA/templates/bounce_invalid_confirmation.txt
TMDA/templates/bounce_missing_pending.txt
TMDA/templates/confirm_accept.txt
TMDA/templates/confirm_request.txt
TMDAng-1.0.3.dist-info/METADATA
TMDAng-1.0.3.dist-info/top_level.txt
TMDAng-1.0.3.dist-info/entry_points.txt
TMDAng-1.0.3.dist-info/DESCRIPTION.rst
TMDAng-1.0.3.dist-info/metadata.json
TMDAng-1.0.3.dist-info/WHEEL
TMDAng-1.0.3.dist-info/RECORD
