Metadata-Version: 2.0
Name: TMDAng
Version: 1.0.3
Summary: The Tagged Message Delivery Agent (TMDA) is a set of anti-spam measures, including white-listing, black-listing,challenge-response, and tagged addresses
Home-page: http://tmda.net/
Author: Jason R. Mastaler, Kevin Goodsell, Paul Jimenez, and others
Author-email: pj@place.org
License: UNKNOWN
Platform: UNKNOWN
Classifier: Development Status :: 4 - Beta
Classifier: Environment :: Console
Classifier: License :: OSI Approved :: GNU General Public License v2 or later (GPLv2+)
Classifier: Intended Audience :: System Administrators
Classifier: Natural Language :: English
Classifier: Operating System :: MacOS :: MacOS X
Classifier: Operating System :: Microsoft :: Windows
Classifier: Operating System :: POSIX
Classifier: Programming Language :: Python :: 3.4
Classifier: Programming Language :: Python :: Implementation :: CPython
Classifier: Topic :: Communications :: Email :: Filters
Classifier: Topic :: Internet :: Proxy Servers
Requires-Dist: pyOpenSSL (>=0.14)
Requires-Dist: python-pam (>=1.8.2)
